README.md
setup.py
cveguess/__init__.py
cveguess/__main__.py
cveguess/cmdline.py
cveguess/cveguess.py
cveguess/github.py
cveguess/nvd.py
cveguess/tables.py
cveguess.egg-info/PKG-INFO
cveguess.egg-info/SOURCES.txt
cveguess.egg-info/dependency_links.txt
cveguess.egg-info/not-zip-safe
cveguess.egg-info/requires.txt
cveguess.egg-info/top_level.txt