Metadata-Version: 1.2
Name: cveguess
Version: 0.0.2a0
Summary: CVE exploit guesser
Home-page: https://github.com/mtnalonso/cveguess
Author: Martin Alonso Vilar
Author-email: mtnalonso@protonmail.com
License: GNU General Public License v3 (GPLv3)
Platform: UNKNOWN
Classifier: Development Status :: 2 - Pre-Alpha
Classifier: Environment :: Console
Classifier: Intended Audience :: Developers
Classifier: License :: OSI Approved :: GNU General Public License v3 (GPLv3)
Classifier: Operating System :: POSIX :: Linux
Classifier: Programming Language :: Python :: 3.8
Classifier: Programming Language :: Python :: Implementation :: PyPy
Classifier: Topic :: Software Development :: Libraries :: Python Modules
Requires-Python: >=3.8
